thirteen_gpu/__init__.py
thirteen_gpu/add_new_worker.py
thirteen_gpu/dashboard.py
thirteen_gpu/definition.py
thirteen_gpu/delete.py
thirteen_gpu/disk_usage_check.py
thirteen_gpu/job.py
thirteen_gpu/main.py
thirteen_gpu/project.py
thirteen_gpu/ssh.py
thirteen_gpu/submit.py
thirteen_gpu/vast.py
thirteen_gpu/vast_sdk.py
thirteen_gpu/worker.py
thirteen_gpu-0.0.15.dist-info/METADATA
thirteen_gpu-0.0.15.dist-info/WHEEL
thirteen_gpu-0.0.15.dist-info/entry_points.txt
thirteen_gpu-0.0.15.dist-info/top_level.txt
thirteen_gpu-0.0.15.dist-info/RECORD
