Metadata-Version: 2.4
Name: thirteen_gpu
Version: 0.0.15
Summary: simple gpu scheduler
Home-page: https://github.com/thirteen-ai/simple_gpu_scheduler
Download-URL: https://github.com/thirteen-ai/simple_gpu_scheduler/archive/master.zip
Author: seil.na
Author-email: seil.na@thirteen.ai
Requires-Python: >=3
Requires-Dist: fastapi
Requires-Dist: paramiko
Requires-Dist: uvicorn
Provides-Extra: vast
Requires-Dist: vastai-sdk>=0.3.1; extra == "vast"
Dynamic: author
Dynamic: author-email
Dynamic: download-url
Dynamic: home-page
Dynamic: provides-extra
Dynamic: requires-dist
Dynamic: requires-python
Dynamic: summary
